shopcloud_metric/__init__.py
shopcloud_metric/__main__.py
shopcloud_metric/cli.py
shopcloud_metric-0.2.1.data/scripts/metric
shopcloud_metric-0.2.1.dist-info/LICENSE
shopcloud_metric-0.2.1.dist-info/METADATA
shopcloud_metric-0.2.1.dist-info/WHEEL
shopcloud_metric-0.2.1.dist-info/top_level.txt
shopcloud_metric-0.2.1.dist-info/RECORD
