Metadata-Version: 2.1
Name: shopcloud-metric
Version: 0.2.1
Summary: CLI tool for Metrics
Home-page: https://github.com/Talk-Point/shopcloud-metric-cli
Author: Konstantin Stoldt
Author-email: konstantin.stoldt@talk-point.de
License: MIT
Keywords: CLI
Platform: UNKNOWN
Requires-Dist: requests
Requires-Dist: shopcloud-secrethub
